COPYING
MANIFEST.in
README.txt
__init__.py
__main__.py
connect.py
container.py
context.py
desktop.py
document.py
exchange.py
find_ooo.py
libraries.py
library.py
setup.py
ooo_macro_exchange.egg-info/PKG-INFO
ooo_macro_exchange.egg-info/SOURCES.txt
ooo_macro_exchange.egg-info/dependency_links.txt
ooo_macro_exchange.egg-info/entry_points.txt
ooo_macro_exchange.egg-info/top_level.txt