Metadata-Version: 1.0
Name: ooo-macro-exchange
Version: 0.2.2
Summary:  Routines and CLI to facilitate injection/extraction of OpenOffice.org macros.
Home-page: http://github.com/intuited/ooo-macro-exchange
Author: Ted Tibbetts
Author-email: intuited@gmail.com
License: UNKNOWN
Keywords: ooo,openoffice,openoffice.org,macro,basic,starbasic,oobasic,uno
Platform: UNKNOWN
Classifier: Development Status :: 4 - Beta
Classifier: Intended Audience :: Developers
Classifier: License :: OSI Approved :: BSD License
Classifier: Operating System :: OS Independent
Classifier: Programming Language :: Basic
Classifier: Programming Language :: Python
Classifier: Programming Language :: Python :: 2
Classifier: Topic :: Software Development :: Libraries :: Python Modules
Classifier: Topic :: Office/Business :: Office Suites
Classifier: Topic :: Utilities
